convertio/__init__.py
convertio/client.py
convertio/client_test.py
convertio/languages.py
convertio/models/__init__.py
convertio/models/models_test.py
convertio/models/parameters.py
convertio/models/responses.py
convertio_python-0.1.2.dist-info/METADATA
convertio_python-0.1.2.dist-info/WHEEL
convertio_python-0.1.2.dist-info/RECORD
