Metadata-Version: 2.1
Name: convertio-python
Version: 0.1.2
Summary: Convertio APIs Client Library for Python
Author: Okba Boularaoui
Author-email: okba2fb@gmail.com
Requires-Python: >=3.8,<4.0
Classifier: Programming Language :: Python :: 3
Classifier: Programming Language :: Python :: 3.8
Classifier: Programming Language :: Python :: 3.9
Classifier: Programming Language :: Python :: 3.10
Classifier: Programming Language :: Python :: 3.11
Requires-Dist: httpx (>=0.24.1,<0.25.0)
Requires-Dist: pydantic (>=1.10.12,<1.11.0)
